transparentlogs_pymerkle/__init__.py
transparentlogs_pymerkle/constants.py
transparentlogs_pymerkle/hashing.py
transparentlogs_pymerkle/proof.py
transparentlogs_pymerkle/utils.py
transparentlogs_pymerkle/tree/__init__.py
transparentlogs_pymerkle/tree/base.py
transparentlogs_pymerkle/tree/sakura.py
transparentlogs_pymerkle-0.0.3.dist-info/METADATA
transparentlogs_pymerkle-0.0.3.dist-info/WHEEL
transparentlogs_pymerkle-0.0.3.dist-info/licenses/LICENSE
transparentlogs_pymerkle-0.0.3.dist-info/RECORD
